nco/sinlt.v
module sinlt(
    input [7:0] phase, 
    output reg [7:0] val // it needs to be reg type as we should drive the output from somewhere
    );

always @(phase) begin
//https://www.jdoodle.com/execute-nodejs-online
//for(i=0;i<256;i++) { console.log("8'b" + i.toString(2).padStart(8, '0')+": val = " + Math.round(128+Math.sin(i*2*Math.PI/256)*127)+";" )}
    case (phase)
        8'b00000000: val = 128;
        8'b00000001: val = 131;
        8'b00000010: val = 134;
        8'b00000011: val = 137;
        8'b00000100: val = 140;
        8'b00000101: val = 144;
        8'b00000110: val = 147;
        8'b00000111: val = 150;
        8'b00001000: val = 153;
        8'b00001001: val = 156;
        8'b00001010: val = 159;
        8'b00001011: val = 162;
        8'b00001100: val = 165;
        8'b00001101: val = 168;
        8'b00001110: val = 171;
        8'b00001111: val = 174;
        8'b00010000: val = 177;
        8'b00010001: val = 179;
        8'b00010010: val = 182;
        8'b00010011: val = 185;
        8'b00010100: val = 188;
        8'b00010101: val = 191;
        8'b00010110: val = 193;
        8'b00010111: val = 196;
        8'b00011000: val = 199;
        8'b00011001: val = 201;
        8'b00011010: val = 204;
        8'b00011011: val = 206;
        8'b00011100: val = 209;
        8'b00011101: val = 211;
        8'b00011110: val = 213;
        8'b00011111: val = 216;
        8'b00100000: val = 218;
        8'b00100001: val = 220;
        8'b00100010: val = 222;
        8'b00100011: val = 224;
        8'b00100100: val = 226;
        8'b00100101: val = 228;
        8'b00100110: val = 230;
        8'b00100111: val = 232;
        8'b00101000: val = 234;
        8'b00101001: val = 235;
        8'b00101010: val = 237;
        8'b00101011: val = 239;
        8'b00101100: val = 240;
        8'b00101101: val = 241;
        8'b00101110: val = 243;
        8'b00101111: val = 244;
        8'b00110000: val = 245;
        8'b00110001: val = 246;
        8'b00110010: val = 248;
        8'b00110011: val = 249;
        8'b00110100: val = 250;
        8'b00110101: val = 250;
        8'b00110110: val = 251;
        8'b00110111: val = 252;
        8'b00111000: val = 253;
        8'b00111001: val = 253;
        8'b00111010: val = 254;
        8'b00111011: val = 254;
        8'b00111100: val = 254;
        8'b00111101: val = 255;
        8'b00111110: val = 255;
        8'b00111111: val = 255;
        8'b01000000: val = 255;
        8'b01000001: val = 255;
        8'b01000010: val = 255;
        8'b01000011: val = 255;
        8'b01000100: val = 254;
        8'b01000101: val = 254;
        8'b01000110: val = 254;
        8'b01000111: val = 253;
        8'b01001000: val = 253;
        8'b01001001: val = 252;
        8'b01001010: val = 251;
        8'b01001011: val = 250;
        8'b01001100: val = 250;
        8'b01001101: val = 249;
        8'b01001110: val = 248;
        8'b01001111: val = 246;
        8'b01010000: val = 245;
        8'b01010001: val = 244;
        8'b01010010: val = 243;
        8'b01010011: val = 241;
        8'b01010100: val = 240;
        8'b01010101: val = 239;
        8'b01010110: val = 237;
        8'b01010111: val = 235;
        8'b01011000: val = 234;
        8'b01011001: val = 232;
        8'b01011010: val = 230;
        8'b01011011: val = 228;
        8'b01011100: val = 226;
        8'b01011101: val = 224;
        8'b01011110: val = 222;
        8'b01011111: val = 220;
        8'b01100000: val = 218;
        8'b01100001: val = 216;
        8'b01100010: val = 213;
        8'b01100011: val = 211;
        8'b01100100: val = 209;
        8'b01100101: val = 206;
        8'b01100110: val = 204;
        8'b01100111: val = 201;
        8'b01101000: val = 199;
        8'b01101001: val = 196;
        8'b01101010: val = 193;
        8'b01101011: val = 191;
        8'b01101100: val = 188;
        8'b01101101: val = 185;
        8'b01101110: val = 182;
        8'b01101111: val = 179;
        8'b01110000: val = 177;
        8'b01110001: val = 174;
        8'b01110010: val = 171;
        8'b01110011: val = 168;
        8'b01110100: val = 165;
        8'b01110101: val = 162;
        8'b01110110: val = 159;
        8'b01110111: val = 156;
        8'b01111000: val = 153;
        8'b01111001: val = 150;
        8'b01111010: val = 147;
        8'b01111011: val = 144;
        8'b01111100: val = 140;
        8'b01111101: val = 137;
        8'b01111110: val = 134;
        8'b01111111: val = 131;
        8'b10000000: val = 128;
        8'b10000001: val = 125;
        8'b10000010: val = 122;
        8'b10000011: val = 119;
        8'b10000100: val = 116;
        8'b10000101: val = 112;
        8'b10000110: val = 109;
        8'b10000111: val = 106;
        8'b10001000: val = 103;
        8'b10001001: val = 100;
        8'b10001010: val = 97;
        8'b10001011: val = 94;
        8'b10001100: val = 91;
        8'b10001101: val = 88;
        8'b10001110: val = 85;
        8'b10001111: val = 82;
        8'b10010000: val = 79;
        8'b10010001: val = 77;
        8'b10010010: val = 74;
        8'b10010011: val = 71;
        8'b10010100: val = 68;
        8'b10010101: val = 65;
        8'b10010110: val = 63;
        8'b10010111: val = 60;
        8'b10011000: val = 57;
        8'b10011001: val = 55;
        8'b10011010: val = 52;
        8'b10011011: val = 50;
        8'b10011100: val = 47;
        8'b10011101: val = 45;
        8'b10011110: val = 43;
        8'b10011111: val = 40;
        8'b10100000: val = 38;
        8'b10100001: val = 36;
        8'b10100010: val = 34;
        8'b10100011: val = 32;
        8'b10100100: val = 30;
        8'b10100101: val = 28;
        8'b10100110: val = 26;
        8'b10100111: val = 24;
        8'b10101000: val = 22;
        8'b10101001: val = 21;
        8'b10101010: val = 19;
        8'b10101011: val = 17;
        8'b10101100: val = 16;
        8'b10101101: val = 15;
        8'b10101110: val = 13;
        8'b10101111: val = 12;
        8'b10110000: val = 11;
        8'b10110001: val = 10;
        8'b10110010: val = 8;
        8'b10110011: val = 7;
        8'b10110100: val = 6;
        8'b10110101: val = 6;
        8'b10110110: val = 5;
        8'b10110111: val = 4;
        8'b10111000: val = 3;
        8'b10111001: val = 3;
        8'b10111010: val = 2;
        8'b10111011: val = 2;
        8'b10111100: val = 2;
        8'b10111101: val = 1;
        8'b10111110: val = 1;
        8'b10111111: val = 1;
        8'b11000000: val = 1;
        8'b11000001: val = 1;
        8'b11000010: val = 1;
        8'b11000011: val = 1;
        8'b11000100: val = 2;
        8'b11000101: val = 2;
        8'b11000110: val = 2;
        8'b11000111: val = 3;
        8'b11001000: val = 3;
        8'b11001001: val = 4;
        8'b11001010: val = 5;
        8'b11001011: val = 6;
        8'b11001100: val = 6;
        8'b11001101: val = 7;
        8'b11001110: val = 8;
        8'b11001111: val = 10;
        8'b11010000: val = 11;
        8'b11010001: val = 12;
        8'b11010010: val = 13;
        8'b11010011: val = 15;
        8'b11010100: val = 16;
        8'b11010101: val = 17;
        8'b11010110: val = 19;
        8'b11010111: val = 21;
        8'b11011000: val = 22;
        8'b11011001: val = 24;
        8'b11011010: val = 26;
        8'b11011011: val = 28;
        8'b11011100: val = 30;
        8'b11011101: val = 32;
        8'b11011110: val = 34;
        8'b11011111: val = 36;
        8'b11100000: val = 38;
        8'b11100001: val = 40;
        8'b11100010: val = 43;
        8'b11100011: val = 45;
        8'b11100100: val = 47;
        8'b11100101: val = 50;
        8'b11100110: val = 52;
        8'b11100111: val = 55;
        8'b11101000: val = 57;
        8'b11101001: val = 60;
        8'b11101010: val = 63;
        8'b11101011: val = 65;
        8'b11101100: val = 68;
        8'b11101101: val = 71;
        8'b11101110: val = 74;
        8'b11101111: val = 77;
        8'b11110000: val = 79;
        8'b11110001: val = 82;
        8'b11110010: val = 85;
        8'b11110011: val = 88;
        8'b11110100: val = 91;
        8'b11110101: val = 94;
        8'b11110110: val = 97;
        8'b11110111: val = 100;
        8'b11111000: val = 103;
        8'b11111001: val = 106;
        8'b11111010: val = 109;
        8'b11111011: val = 112;
        8'b11111100: val = 116;
        8'b11111101: val = 119;
        8'b11111110: val = 122;
        8'b11111111: val = 125;
    endcase
end

endmodule

nco/nco.v
module nco(input clk, input [15:0] fcw, output [15:0] m, output s, output [7:0] sine);
    
    reg [11:0] acc = 0;
    reg [7:0] phase = 0;
    wire [7:0] sss;

    sinlt i1 (phase, sss);

    always @(posedge clk) begin
        acc <= acc + fcw;
        phase <= acc[11:4];
    end

    assign m = acc;
    assign s = acc[11];
    assign sine = sss;

endmodule

nco/nco_tb.v
module test();
    reg clk = 0;
    reg [15:0] fcw = 10;
    wire [15:0] ppp;
    wire signal;
    wire [7:0] osin;

    nco u(clk, fcw, ppp, signal, osin);

    always
        #1  clk = ~clk;

    initial begin
        $display("Starting NCO");
        $monitor("Output Value %h", ppp);
        #1000 assign fcw = 30;
        #1000 $finish;

    end

    initial begin
        $dumpfile("nco.vcd");
        $dumpvars(0, test);
    end    

endmodule

nco/nco.vcd
$date
	Fri Jun 21 09:31:39 2024
$end
$version
	Icarus Verilog
$end
$timescale
	1s
$end
$scope module test $end
$var wire 1 ! signal $end
$var wire 16 " ppp [15:0] $end
$var wire 8 # osin [7:0] $end
$var reg 1 $ clk $end
$var reg 16 % fcw [15:0] $end
$scope module u $end
$var wire 1 $ clk $end
$var wire 16 & fcw [15:0] $end
$var wire 8 ' sine [7:0] $end
$var wire 8 ( sss [7:0] $end
$var wire 1 ! s $end
$var wire 16 ) m [15:0] $end
$var reg 12 * acc [11:0] $end
$var reg 8 + phase [7:0] $end
$scope module i1 $end
$var wire 8 , phase [7:0] $end
$var reg 8 - val [7:0] $end
$upscope $end
$upscope $end
$upscope $end
$enddefinitions $end
$comment Show the parameter values. $end
$dumpall
$end
#0
$dumpvars
b10000000 -
b0 ,
b0 +
b0 *
b0 )
b10000000 (
b10000000 '
b1010 &
b1010 %
0$
b10000000 #
b0 "
0!
$end
#1
b1010 "
b1010 )
b1010 *
1$
#2
0$
#3
b10100 "
b10100 )
b10100 *
1$
#4
0$
#5
b10000011 #
b10000011 '
b10000011 (
b10000011 -
b1 +
b1 ,
b11110 "
b11110 )
b11110 *
1$
#6
0$
#7
b101000 "
b101000 )
b101000 *
1$
#8
0$
#9
b10000110 #
b10000110 '
b10000110 (
b10000110 -
b10 +
b10 ,
b110010 "
b110010 )
b110010 *
1$
#10
0$
#11
b10001001 #
b10001001 '
b10001001 (
b10001001 -
b11 +
b11 ,
b111100 "
b111100 )
b111100 *
1$
#12
0$
#13
b1000110 "
b1000110 )
b1000110 *
1$
#14
0$
#15
b10001100 #
b10001100 '
b10001100 (
b10001100 -
b100 +
b100 ,
b1010000 "
b1010000 )
b1010000 *
1$
#16
0$
#17
b10010000 #
b10010000 '
b10010000 (
b10010000 -
b101 +
b101 ,
b1011010 "
b1011010 )
b1011010 *
1$
#18
0$
#19
b1100100 "
b1100100 )
b1100100 *
1$
#20
0$
#21
b10010011 #
b10010011 '
b10010011 (
b10010011 -
b110 +
b110 ,
b1101110 "
b1101110 )
b1101110 *
1$
#22
0$
#23
b1111000 "
b1111000 )
b1111000 *
1$
#24
0$
#25
b10010110 #
b10010110 '
b10010110 (
b10010110 -
b111 +
b111 ,
b10000010 "
b10000010 )
b10000010 *
1$
#26
0$
#27
b10011001 #
b10011001 '
b10011001 (
b10011001 -
b1000 +
b1000 ,
b10001100 "
b10001100 )
b10001100 *
1$
#28
0$
#29
b10010110 "
b10010110 )
b10010110 *
1$
#30
0$
#31
b10011100 #
b10011100 '
b10011100 (
b10011100 -
b1001 +
b1001 ,
b10100000 "
b10100000 )
b10100000 *
1$
#32
0$
#33
b10011111 #
b10011111 '
b10011111 (
b10011111 -
b1010 +
b1010 ,
b10101010 "
b10101010 )
b10101010 *
1$
#34
0$
#35
b10110100 "
b10110100 )
b10110100 *
1$
#36
0$
#37
b10100010 #
b10100010 '
b10100010 (
b10100010 -
b1011 +
b1011 ,
b10111110 "
b10111110 )
b10111110 *
1$
#38
0$
#39
b11001000 "
b11001000 )
b11001000 *
1$
#40
0$
#41
b10100101 #
b10100101 '
b10100101 (
b10100101 -
b1100 +
b1100 ,
b11010010 "
b11010010 )
b11010010 *
1$
#42
0$
#43
b10101000 #
b10101000 '
b10101000 (
b10101000 -
b1101 +
b1101 ,
b11011100 "
b11011100 )
b11011100 *
1$
#44
0$
#45
b11100110 "
b11100110 )
b11100110 *
1$
#46
0$
#47
b10101011 #
b10101011 '
b10101011 (
b10101011 -
b1110 +
b1110 ,
b11110000 "
b11110000 )
b11110000 *
1$
#48
0$
#49
b10101110 #
b10101110 '
b10101110 (
b10101110 -
b1111 +
b1111 ,
b11111010 "
b11111010 )
b11111010 *
1$
#50
0$
#51
b100000100 "
b100000100 )
b100000100 *
1$
#52
0$
#53
b10110001 #
b10110001 '
b10110001 (
b10110001 -
b10000 +
b10000 ,
b100001110 "
b100001110 )
b100001110 *
1$
#54
0$
#55
b100011000 "
b100011000 )
b100011000 *
1$
#56
0$
#57
b10110011 #
b10110011 '
b10110011 (
b10110011 -
b10001 +
b10001 ,
b100100010 "
b100100010 )
b100100010 *
1$
#58
0$
#59
b10110110 #
b10110110 '
b10110110 (
b10110110 -
b10010 +
b10010 ,
b100101100 "
b100101100 )
b100101100 *
1$
#60
0$
#61
b100110110 "
b100110110 )
b100110110 *
1$
#62
0$
#63
b10111001 #
b10111001 '
b10111001 (
b10111001 -
b10011 +
b10011 ,
b101000000 "
b101000000 )
b101000000 *
1$
#64
0$
#65
b10111100 #
b10111100 '
b10111100 (
b10111100 -
b10100 +
b10100 ,
b101001010 "
b101001010 )
b101001010 *
1$
#66
0$
#67
b101010100 "
b101010100 )
b101010100 *
1$
#68
0$
#69
b10111111 #
b10111111 '
b10111111 (
b10111111 -
b10101 +
b10101 ,
b101011110 "
b101011110 )
b101011110 *
1$
#70
0$
#71
b101101000 "
b101101000 )
b101101000 *
1$
#72
0$
#73
b11000001 #
b11000001 '
b11000001 (
b11000001 -
b10110 +
b10110 ,
b101110010 "
b101110010 )
b101110010 *
1$
#74
0$
#75
b11000100 #
b11000100 '
b11000100 (
b11000100 -
b10111 +
b10111 ,
b101111100 "
b101111100 )
b101111100 *
1$
#76
0$
#77
b110000110 "
b110000110 )
b110000110 *
1$
#78
0$
#79
b11000111 #
b11000111 '
b11000111 (
b11000111 -
b11000 +
b11000 ,
b110010000 "
b110010000 )
b110010000 *
1$
#80
0$
#81
b11001001 #
b11001001 '
b11001001 (
b11001001 -
b11001 +
b11001 ,
b110011010 "
b110011010 )
b110011010 *
1$
#82
0$
#83
b110100100 "
b110100100 )
b110100100 *
1$
#84
0$
#85
b11001100 #
b11001100 '
b11001100 (
b11001100 -
b11010 +
b11010 ,
b110101110 "
b110101110 )
b110101110 *
1$
#86
0$
#87
b110111000 "
b110111000 )
b110111000 *
1$
#88
0$
#89
b11001110 #
b11001110 '
b11001110 (
b11001110 -
b11011 +
b11011 ,
b111000010 "
b111000010 )
b111000010 *
1$
#90
0$
#91
b11010001 #
b11010001 '
b11010001 (
b11010001 -
b11100 +
b11100 ,
b111001100 "
b111001100 )
b111001100 *
1$
#92
0$
#93
b111010110 "
b111010110 )
b111010110 *
1$
#94
0$
#95
b11010011 #
b11010011 '
b11010011 (
b11010011 -
b11101 +
b11101 ,
b111100000 "
b111100000 )
b111100000 *
1$
#96
0$
#97
b11010101 #
b11010101 '
b11010101 (
b11010101 -
b11110 +
b11110 ,
b111101010 "
b111101010 )
b111101010 *
1$
#98
0$
#99
b111110100 "
b111110100 )
b111110100 *
1$
#100
0$
#101
b11011000 #
b11011000 '
b11011000 (
b11011000 -
b11111 +
b11111 ,
b111111110 "
b111111110 )
b111111110 *
1$
#102
0$
#103
b1000001000 "
b1000001000 )
b1000001000 *
1$
#104
0$
#105
b11011010 #
b11011010 '
b11011010 (
b11011010 -
b100000 +
b100000 ,
b1000010010 "
b1000010010 )
b1000010010 *
1$
#106
0$
#107
b11011100 #
b11011100 '
b11011100 (
b11011100 -
b100001 +
b100001 ,
b1000011100 "
b1000011100 )
b1000011100 *
1$
#108
0$
#109
b1000100110 "
b1000100110 )
b1000100110 *
1$
#110
0$
#111
b11011110 #
b11011110 '
b11011110 (
b11011110 -
b100010 +
b100010 ,
b1000110000 "
b1000110000 )
b1000110000 *
1$
#112
0$
#113
b11100000 #
b11100000 '
b11100000 (
b11100000 -
b100011 +
b100011 ,
b1000111010 "
b1000111010 )
b1000111010 *
1$
#114
0$
#115
b1001000100 "
b1001000100 )
b1001000100 *
1$
#116
0$
#117
b11100010 #
b11100010 '
b11100010 (
b11100010 -
b100100 +
b100100 ,
b1001001110 "
b1001001110 )
b1001001110 *
1$
#118
0$
#119
b1001011000 "
b1001011000 )
b1001011000 *
1$
#120
0$
#121
b11100100 #
b11100100 '
b11100100 (
b11100100 -
b100101 +
b100101 ,
b1001100010 "
b1001100010 )
b1001100010 *
1$
#122
0$
#123
b11100110 #
b11100110 '
b11100110 (
b11100110 -
b100110 +
b100110 ,
b1001101100 "
b1001101100 )
b1001101100 *
1$
#124
0$
#125
b1001110110 "
b1001110110 )
b1001110110 *
1$
#126
0$
#127
b11101000 #
b11101000 '
b11101000 (
b11101000 -
b100111 +
b100111 ,
b1010000000 "
b1010000000 )
b1010000000 *
1$
#128
0$
#129
b11101010 #
b11101010 '
b11101010 (
b11101010 -
b101000 +
b101000 ,
b1010001010 "
b1010001010 )
b1010001010 *
1$
#130
0$
#131
b1010010100 "
b1010010100 )
b1010010100 *
1$
#132
0$
#133
b11101011 #
b11101011 '
b11101011 (
b11101011 -
b101001 +
b101001 ,
b1010011110 "
b1010011110 )
b1010011110 *
1$
#134
0$
#135
b1010101000 "
b1010101000 )
b1010101000 *
1$
#136
0$
#137
b11101101 #
b11101101 '
b11101101 (
b11101101 -
b101010 +
b101010 ,
b1010110010 "
b1010110010 )
b1010110010 *
1$
#138
0$
#139
b11101111 #
b11101111 '
b11101111 (
b11101111 -
b101011 +
b101011 ,
b1010111100 "
b1010111100 )
b1010111100 *
1$
#140
0$
#141
b1011000110 "
b1011000110 )
b1011000110 *
1$
#142
0$
#143
b11110000 #
b11110000 '
b11110000 (
b11110000 -
b101100 +
b101100 ,
b1011010000 "
b1011010000 )
b1011010000 *
1$
#144
0$
#145
b11110001 #
b11110001 '
b11110001 (
b11110001 -
b101101 +
b101101 ,
b1011011010 "
b1011011010 )
b1011011010 *
1$
#146
0$
#147
b1011100100 "
b1011100100 )
b1011100100 *
1$
#148
0$
#149
b11110011 #
b11110011 '
b11110011 (
b11110011 -
b101110 +
b101110 ,
b1011101110 "
b1011101110 )
b1011101110 *
1$
#150
0$
#151
b1011111000 "
b1011111000 )
b1011111000 *
1$
#152
0$
#153
b11110100 #
b11110100 '
b11110100 (
b11110100 -
b101111 +
b101111 ,
b1100000010 "
b1100000010 )
b1100000010 *
1$
#154
0$
#155
b11110101 #
b11110101 '
b11110101 (
b11110101 -
b110000 +
b110000 ,
b1100001100 "
b1100001100 )
b1100001100 *
1$
#156
0$
#157
b1100010110 "
b1100010110 )
b1100010110 *
1$
#158
0$
#159
b11110110 #
b11110110 '
b11110110 (
b11110110 -
b110001 +
b110001 ,
b1100100000 "
b1100100000 )
b1100100000 *
1$
#160
0$
#161
b11111000 #
b11111000 '
b11111000 (
b11111000 -
b110010 +
b110010 ,
b1100101010 "
b1100101010 )
b1100101010 *
1$
#162
0$
#163
b1100110100 "
b1100110100 )
b1100110100 *
1$
#164
0$
#165
b11111001 #
b11111001 '
b11111001 (
b11111001 -
b110011 +
b110011 ,
b1100111110 "
b1100111110 )
b1100111110 *
1$
#166
0$
#167
b1101001000 "
b1101001000 )
b1101001000 *
1$
#168
0$
#169
b11111010 #
b11111010 '
b11111010 (
b11111010 -
b110100 +
b110100 ,
b1101010010 "
b1101010010 )
b1101010010 *
1$
#170
0$
#171
b110101 +
b110101 ,
b1101011100 "
b1101011100 )
b1101011100 *
1$
#172
0$
#173
b1101100110 "
b1101100110 )
b1101100110 *
1$
#174
0$
#175
b11111011 #
b11111011 '
b11111011 (
b11111011 -
b110110 +
b110110 ,
b1101110000 "
b1101110000 )
b1101110000 *
1$
#176
0$
#177
b11111100 #
b11111100 '
b11111100 (
b11111100 -
b110111 +
b110111 ,
b1101111010 "
b1101111010 )
b1101111010 *
1$
#178
0$
#179
b1110000100 "
b1110000100 )
b1110000100 *
1$
#180
0$
#181
b11111101 #
b11111101 '
b11111101 (
b11111101 -
b111000 +
b111000 ,
b1110001110 "
b1110001110 )
b1110001110 *
1$
#182
0$
#183
b1110011000 "
b1110011000 )
b1110011000 *
1$
#184
0$
#185
b111001 +
b111001 ,
b1110100010 "
b1110100010 )
b1110100010 *
1$
#186
0$
#187
b11111110 #
b11111110 '
b11111110 (
b11111110 -
b111010 +
b111010 ,
b1110101100 "
b1110101100 )
b1110101100 *
1$
#188
0$
#189
b1110110110 "
b1110110110 )
b1110110110 *
1$
#190
0$
#191
b111011 +
b111011 ,
b1111000000 "
b1111000000 )
b1111000000 *
1$
#192
0$
#193
b111100 +
b111100 ,
b1111001010 "
b1111001010 )
b1111001010 *
1$
#194
0$
#195
b1111010100 "
b1111010100 )
b1111010100 *
1$
#196
0$
#197
b11111111 #
b11111111 '
b11111111 (
b11111111 -
b111101 +
b111101 ,
b1111011110 "
b1111011110 )
b1111011110 *
1$
#198
0$
#199
b1111101000 "
b1111101000 )
b1111101000 *
1$
#200
0$
#201
b111110 +
b111110 ,
b1111110010 "
b1111110010 )
b1111110010 *
1$
#202
0$
#203
b111111 +
b111111 ,
b1111111100 "
b1111111100 )
b1111111100 *
1$
#204
0$
#205
b10000000110 "
b10000000110 )
b10000000110 *
1$
#206
0$
#207
b1000000 +
b1000000 ,
b10000010000 "
b10000010000 )
b10000010000 *
1$
#208
0$
#209
b1000001 +
b1000001 ,
b10000011010 "
b10000011010 )
b10000011010 *
1$
#210
0$
#211
b10000100100 "
b10000100100 )
b10000100100 *
1$
#212
0$
#213
b1000010 +
b1000010 ,
b10000101110 "
b10000101110 )
b10000101110 *
1$
#214
0$
#215
b10000111000 "
b10000111000 )
b10000111000 *
1$
#216
0$
#217
b1000011 +
b1000011 ,
b10001000010 "
b10001000010 )
b10001000010 *
1$
#218
0$
#219
b11111110 #
b11111110 '
b11111110 (
b11111110 -
b1000100 +
b1000100 ,
b10001001100 "
b10001001100 )
b10001001100 *
1$
#220
0$
#221
b10001010110 "
b10001010110 )
b10001010110 *
1$
#222
0$
#223
b1000101 +
b1000101 ,
b10001100000 "
b10001100000 )
b10001100000 *
1$
#224
0$
#225
b1000110 +
b1000110 ,
b10001101010 "
b10001101010 )
b10001101010 *
1$
#226
0$
#227
b10001110100 "
b10001110100 )
b10001110100 *
1$
#228
0$
#229
b11111101 #
b11111101 '
b11111101 (
b11111101 -
b1000111 +
b1000111 ,
b10001111110 "
b10001111110 )
b10001111110 *
1$
#230
0$
#231
b10010001000 "
b10010001000 )
b10010001000 *
1$
#232
0$
#233
b1001000 +
b1001000 ,
b10010010010 "
b10010010010 )
b10010010010 *
1$
#234
0$
#235
b11111100 #
b11111100 '
b11111100 (
b11111100 -
b1001001 +
b1001001 ,
b10010011100 "
b10010011100 )
b10010011100 *
1$
#236
0$
#237
b10010100110 "
b10010100110 )
b10010100110 *
1$
#238
0$
#239
b11111011 #
b11111011 '
b11111011 (
b11111011 -
b1001010 +
b1001010 ,
b10010110000 "
b10010110000 )
b10010110000 *
1$
#240
0$
#241
b11111010 #
b11111010 '
b11111010 (
b11111010 -
b1001011 +
b1001011 ,
b10010111010 "
b10010111010 )
b10010111010 *
1$
#242
0$
#243
b10011000100 "
b10011000100 )
b10011000100 *
1$
#244
0$
#245
b1001100 +
b1001100 ,
b10011001110 "
b10011001110 )
b10011001110 *
1$
#246
0$
#247
b10011011000 "
b10011011000 )
b10011011000 *
1$
#248
0$
#249
b11111001 #
b11111001 '
b11111001 (
b11111001 -
b1001101 +
b1001101 ,
b10011100010 "
b10011100010 )
b10011100010 *
1$
#250
0$
#251
b11111000 #
b11111000 '
b11111000 (
b11111000 -
b1001110 +
b1001110 ,
b10011101100 "
b10011101100 )
b10011101100 *
1$
#252
0$
#253
b10011110110 "
b10011110110 )
b10011110110 *
1$
#254
0$
#255
b11110110 #
b11110110 '
b11110110 (
b11110110 -
b1001111 +
b1001111 ,
b10100000000 "
b10100000000 )
b10100000000 *
1$
#256
0$
#257
b11110101 #
b11110101 '
b11110101 (
b11110101 -
b1010000 +
b1010000 ,
b10100001010 "
b10100001010 )
b10100001010 *
1$
#258
0$
#259
b10100010100 "
b10100010100 )
b10100010100 *
1$
#260
0$
#261
b11110100 #
b11110100 '
b11110100 (
b11110100 -
b1010001 +
b1010001 ,
b10100011110 "
b10100011110 )
b10100011110 *
1$
#262
0$
#263
b10100101000 "
b10100101000 )
b10100101000 *
1$
#264
0$
#265
b11110011 #
b11110011 '
b11110011 (
b11110011 -
b1010010 +
b1010010 ,
b10100110010 "
b10100110010 )
b10100110010 *
1$
#266
0$
#267
b11110001 #
b11110001 '
b11110001 (
b11110001 -
b1010011 +
b1010011 ,
b10100111100 "
b10100111100 )
b10100111100 *
1$
#268
0$
#269
b10101000110 "
b10101000110 )
b10101000110 *
1$
#270
0$
#271
b11110000 #
b11110000 '
b11110000 (
b11110000 -
b1010100 +
b1010100 ,
b10101010000 "
b10101010000 )
b10101010000 *
1$
#272
0$
#273
b11101111 #
b11101111 '
b11101111 (
b11101111 -
b1010101 +
b1010101 ,
b10101011010 "
b10101011010 )
b10101011010 *
1$
#274
0$
#275
b10101100100 "
b10101100100 )
b10101100100 *
1$
#276
0$
#277
b11101101 #
b11101101 '
b11101101 (
b11101101 -
b1010110 +
b1010110 ,
b10101101110 "
b10101101110 )
b10101101110 *
1$
#278
0$
#279
b10101111000 "
b10101111000 )
b10101111000 *
1$
#280
0$
#281
b11101011 #
b11101011 '
b11101011 (
b11101011 -
b1010111 +
b1010111 ,
b10110000010 "
b10110000010 )
b10110000010 *
1$
#282
0$
#283
b11101010 #
b11101010 '
b11101010 (
b11101010 -
b1011000 +
b1011000 ,
b10110001100 "
b10110001100 )
b10110001100 *
1$
#284
0$
#285
b10110010110 "
b10110010110 )
b10110010110 *
1$
#286
0$
#287
b11101000 #
b11101000 '
b11101000 (
b11101000 -
b1011001 +
b1011001 ,
b10110100000 "
b10110100000 )
b10110100000 *
1$
#288
0$
#289
b11100110 #
b11100110 '
b11100110 (
b11100110 -
b1011010 +
b1011010 ,
b10110101010 "
b10110101010 )
b10110101010 *
1$
#290
0$
#291
b10110110100 "
b10110110100 )
b10110110100 *
1$
#292
0$
#293
b11100100 #
b11100100 '
b11100100 (
b11100100 -
b1011011 +
b1011011 ,
b10110111110 "
b10110111110 )
b10110111110 *
1$
#294
0$
#295
b10111001000 "
b10111001000 )
b10111001000 *
1$
#296
0$
#297
b11100010 #
b11100010 '
b11100010 (
b11100010 -
b1011100 +
b1011100 ,
b10111010010 "
b10111010010 )
b10111010010 *
1$
#298
0$
#299
b11100000 #
b11100000 '
b11100000 (
b11100000 -
b1011101 +
b1011101 ,
b10111011100 "
b10111011100 )
b10111011100 *
1$
#300
0$
#301
b10111100110 "
b10111100110 )
b10111100110 *
1$
#302
0$
#303
b11011110 #
b11011110 '
b11011110 (
b11011110 -
b1011110 +
b1011110 ,
b10111110000 "
b10111110000 )
b10111110000 *
1$
#304
0$
#305
b11011100 #
b11011100 '
b11011100 (
b11011100 -
b1011111 +
b1011111 ,
b10111111010 "
b10111111010 )
b10111111010 *
1$
#306
0$
#307
b11000000100 "
b11000000100 )
b11000000100 *
1$
#308
0$
#309
b11011010 #
b11011010 '
b11011010 (
b11011010 -
b1100000 +
b1100000 ,
b11000001110 "
b11000001110 )
b11000001110 *
1$
#310
0$
#311
b11000011000 "
b11000011000 )
b11000011000 *
1$
#312
0$
#313
b11011000 #
b11011000 '
b11011000 (
b11011000 -
b1100001 +
b1100001 ,
b11000100010 "
b11000100010 )
b11000100010 *
1$
#314
0$
#315
b11010101 #
b11010101 '
b11010101 (
b11010101 -
b1100010 +
b1100010 ,
b11000101100 "
b11000101100 )
b11000101100 *
1$
#316
0$
#317
b11000110110 "
b11000110110 )
b11000110110 *
1$
#318
0$
#319
b11010011 #
b11010011 '
b11010011 (
b11010011 -
b1100011 +
b1100011 ,
b11001000000 "
b11001000000 )
b11001000000 *
1$
#320
0$
#321
b11010001 #
b11010001 '
b11010001 (
b11010001 -
b1100100 +
b1100100 ,
b11001001010 "
b11001001010 )
b11001001010 *
1$
#322
0$
#323
b11001010100 "
b11001010100 )
b11001010100 *
1$
#324
0$
#325
b11001110 #
b11001110 '
b11001110 (
b11001110 -
b1100101 +
b1100101 ,
b11001011110 "
b11001011110 )
b11001011110 *
1$
#326
0$
#327
b11001101000 "
b11001101000 )
b11001101000 *
1$
#328
0$
#329
b11001100 #
b11001100 '
b11001100 (
b11001100 -
b1100110 +
b1100110 ,
b11001110010 "
b11001110010 )
b11001110010 *
1$
#330
0$
#331
b11001001 #
b11001001 '
b11001001 (
b11001001 -
b1100111 +
b1100111 ,
b11001111100 "
b11001111100 )
b11001111100 *
1$
#332
0$
#333
b11010000110 "
b11010000110 )
b11010000110 *
1$
#334
0$
#335
b11000111 #
b11000111 '
b11000111 (
b11000111 -
b1101000 +
b1101000 ,
b11010010000 "
b11010010000 )
b11010010000 *
1$
#336
0$
#337
b11000100 #
b11000100 '
b11000100 (
b11000100 -
b1101001 +
b1101001 ,
b11010011010 "
b11010011010 )
b11010011010 *
1$
#338
0$
#339
b11010100100 "
b11010100100 )
b11010100100 *
1$
#340
0$
#341
b11000001 #
b11000001 '
b11000001 (
b11000001 -
b1101010 +
b1101010 ,
b11010101110 "
b11010101110 )
b11010101110 *
1$
#342
0$
#343
b11010111000 "
b11010111000 )
b11010111000 *
1$
#344
0$
#345
b10111111 #
b10111111 '
b10111111 (
b10111111 -
b1101011 +
b1101011 ,
b11011000010 "
b11011000010 )
b11011000010 *
1$
#346
0$
#347
b10111100 #
b10111100 '
b10111100 (
b10111100 -
b1101100 +
b1101100 ,
b11011001100 "
b11011001100 )
b11011001100 *
1$
#348
0$
#349
b11011010110 "
b11011010110 )
b11011010110 *
1$
#350
0$
#351
b10111001 #
b10111001 '
b10111001 (
b10111001 -
b1101101 +
b1101101 ,
b11011100000 "
b11011100000 )
b11011100000 *
1$
#352
0$
